ytpo/__init__.py
ytpo/ytpo.py
ytpo/secrets/client_secret.json
ytpo-1.3.1.dist-info/METADATA
ytpo-1.3.1.dist-info/WHEEL
ytpo-1.3.1.dist-info/entry_points.txt
ytpo-1.3.1.dist-info/top_level.txt
ytpo-1.3.1.dist-info/RECORD
